prim_sync/__init__.py
prim_sync/__main__.py
prim_sync-0.9.1.dist-info/entry_points.txt
prim_sync-0.9.1.dist-info/LICENSE
prim_sync-0.9.1.dist-info/METADATA
prim_sync-0.9.1.dist-info/WHEEL
prim_sync-0.9.1.dist-info/RECORD
