Metadata-Version: 2.3
Name: prim-sync
Version: 0.9.1
Summary: Primitive Sync - Bidirectional and unidirectional sync over SFTP. Multiplatform Python script optimized for the Primitive FTPd Android SFTP server.
License: Apache-2.0
Author: Laszlo Magyar
Author-email: lmagyar1973@gmail.com
Requires-Python: >=3.12,<4.0
Classifier: Development Status :: 4 - Beta
Classifier: Environment :: Console
Classifier: License :: OSI Approved :: Apache Software License
Classifier: Operating System :: OS Independent
Classifier: Programming Language :: Python :: 3
Classifier: Programming Language :: Python :: 3.12
Classifier: Programming Language :: Python :: 3.13
Requires-Dist: paramiko (>=3.5.0,<4.0.0)
Requires-Dist: platformdirs (>=4.3.6,<5.0.0)
Requires-Dist: zeroconf (>=0.136.2,<0.137.0)
Project-URL: Change Log, https://github.com/lmagyar/prim-sync/blob/main/CHANGELOG.md
Project-URL: Repository, https://github.com/lmagyar/prim-sync
